<?xml version="1.0" encoding="UTF-8" standalone="yes"?><bns:Component xmlns:xsi="http://www.w3.org/2001/XMLSchema-instance" xmlns:bns="http://api.platform.boomi.com/" folderFullPath="Cgfns International, Inc./Sandbox Process Library" componentId="0d338959-81cb-4994-9342-4ec66dcebf5e" version="1" name="Workday Customer Submit Response (MAF)" type="profile.xml" createdDate="2019-08-20T14:50:53Z" createdBy="gtopakas@cgfns.org" modifiedDate="2019-08-20T14:50:53Z" modifiedBy="gtopakas@cgfns.org" deleted="false" currentVersion="true" folderName="Sandbox Process Library" folderId="RjoyNjI3MDU5" copiedFromComponentId="083d2191-c4cc-46fd-860c-6cc839b58e5b" copiedFromComponentVersion="2" branchName="main" branchId="QjoyNDQyNTI"><bns:encryptedValues/><bns:description></bns:description><bns:object><XMLProfile xmlns="" modelVersion="2" strict="true"><ProfileProperties><XMLGeneralInfo/><XMLOptions encoding="utf8" implicitElementOrdering="true" parseRespectMaxOccurs="true" respectMinOccurs="false" respectMinOccursAlways="false"/></ProfileProperties><DataElements><XMLElement dataType="character" isMappable="true" isNode="true" key="2" maxOccurs="1" minOccurs="1" name="Submit_Customer_Response" useNamespace="1"><DataFormat><ProfileCharacterFormat/></DataFormat><XMLNSDeclList><XMLNSDeclaration defaultNamespace="false" isMappable="false" isNode="true" key="1"/></XMLNSDeclList><XMLAttribute dataType="character" isMappable="true" isNode="true" key="3" name="version" required="false" useNamespace="1"><DataFormat><ProfileCharacterFormat/></DataFormat></XMLAttribute><XMLElement dataType="character" isMappable="true" isNode="true" key="4" maxOccurs="1" minOccurs="0" name="Customer_Reference" useNamespace="1"><DataFormat><ProfileCharacterFormat/></DataFormat><XMLAttribute dataType="character" isMappable="true" isNode="true" key="5" name="Descriptor" required="false" useNamespace="1"><DataFormat><ProfileCharacterFormat/></DataFormat></XMLAttribute><XMLElement dataType="character" isMappable="true" isNode="true" key="6" maxOccurs="1" minOccurs="0" name="ID" useNamespace="1"><DataFormat><ProfileCharacterFormat/></DataFormat><XMLAttribute dataType="character" isMappable="true" isNode="true" key="7" name="type" required="false" useNamespace="1"><DataFormat><ProfileCharacterFormat/></DataFormat></XMLAttribute></XMLElement><XMLElement dataType="character" isMappable="true" isNode="true" key="8" maxOccurs="1" minOccurs="0" name="ID" useNamespace="1"><DataFormat><ProfileCharacterFormat/></DataFormat><XMLAttribute dataType="character" isMappable="true" isNode="true" key="9" name="type" required="false" useNamespace="1"><DataFormat><ProfileCharacterFormat/></DataFormat></XMLAttribute></XMLElement><XMLElement dataType="character" isMappable="true" isNode="true" key="10" maxOccurs="1" minOccurs="0" name="ID" useNamespace="1"><DataFormat><ProfileCharacterFormat/></DataFormat><XMLAttribute dataType="character" isMappable="true" isNode="true" key="11" name="type" required="false" useNamespace="1"><DataFormat><ProfileCharacterFormat/></DataFormat></XMLAttribute></XMLElement></XMLElement></XMLElement></DataElements><Namespaces><XMLNamespace key="-1" name="Empty Namespace"><Types/></XMLNamespace><XMLNamespace key="1" name="urn:com.workday/bsvc" prefix="ns1"/></Namespaces></XMLProfile></bns:object></bns:Component>