<?xml version="1.0" encoding="UTF-8" standalone="yes"?><bns:Component xmlns:xsi="http://www.w3.org/2001/XMLSchema-instance" xmlns:bns="http://api.platform.boomi.com/" folderFullPath="Cgfns International, Inc./Sandbox Process Library" componentId="10d9c234-7269-4d70-a692-87e30bc21f6f" version="1" name="Sales Order FF to DB Insert" type="transform.map" createdDate="2019-08-21T18:28:41Z" createdBy="gtopakas@cgfns.org" modifiedDate="2019-08-21T18:28:41Z" modifiedBy="gtopakas@cgfns.org" deleted="false" currentVersion="true" folderName="Sandbox Process Library" folderId="RjoyNjI3MDU5" copiedFromComponentId="ee1a39ee-8725-40ea-ab52-2b74d6201bda" copiedFromComponentVersion="4" branchName="main" branchId="QjoyNDQyNTI"><bns:encryptedValues/><bns:description>Map FF data to the DB profile. Because Details table is configured as a child statement the mapping engine will continue to output multiple lines the while the order header details remain the same. Note: there is an important configuration in the DB profile to "Enforce Unique" on the header statement's OrderNum field to prevent duplicate header records in the output.</bns:description><bns:object><Map xmlns="" fromProfile="80b4225f-92bd-4572-bc24-2a2e10edab77" toProfile="b79e44bc-c998-4bd7-b967-1091caa162e6"><Mappings><Mapping fromKey="4" fromKeyPath="*[@key='2']/*[@key='3']/*[@key='4']" fromNamePath="Record/Elements/Order Number" fromType="profile" toKey="8" toKeyPath="*[@key='5']/*[@key='6']/*[@key='8']" toNamePath="Statement/Fields/OrderNum" toType="profile"/><Mapping fromKey="5" fromKeyPath="*[@key='2']/*[@key='3']/*[@key='5']" fromNamePath="Record/Elements/Order Date" fromType="profile" toKey="9" toKeyPath="*[@key='5']/*[@key='6']/*[@key='9']" toNamePath="Statement/Fields/OrderDate" toType="profile"/><Mapping fromKey="6" fromKeyPath="*[@key='2']/*[@key='3']/*[@key='6']" fromNamePath="Record/Elements/Customer Number" fromType="profile" toKey="10" toKeyPath="*[@key='5']/*[@key='6']/*[@key='10']" toNamePath="Statement/Fields/CustomerNum" toType="profile"/><Mapping fromKey="7" fromKeyPath="*[@key='2']/*[@key='3']/*[@key='7']" fromNamePath="Record/Elements/Customer Name" fromType="profile" toKey="11" toKeyPath="*[@key='5']/*[@key='6']/*[@key='11']" toNamePath="Statement/Fields/CustomerName" toType="profile"/><Mapping fromKey="8" fromKeyPath="*[@key='2']/*[@key='3']/*[@key='8']" fromNamePath="Record/Elements/Line Number" fromType="profile" toKey="16" toKeyPath="*[@key='5']/*[@key='12']/*[@key='13']/*[@key='16']" toNamePath="Statement/Statement/Fields/LineNum" toType="profile"/><Mapping fromKey="4" fromKeyPath="*[@key='2']/*[@key='3']/*[@key='4']" fromNamePath="Record/Elements/Order Number" fromType="profile" toKey="15" toKeyPath="*[@key='5']/*[@key='12']/*[@key='13']/*[@key='15']" toNamePath="Statement/Statement/Fields/OrderNum" toType="profile"/><Mapping fromKey="9" fromKeyPath="*[@key='2']/*[@key='3']/*[@key='9']" fromNamePath="Record/Elements/Item Number" fromType="profile" toKey="17" toKeyPath="*[@key='5']/*[@key='12']/*[@key='13']/*[@key='17']" toNamePath="Statement/Statement/Fields/PartNum" toType="profile"/><Mapping fromKey="10" fromKeyPath="*[@key='2']/*[@key='3']/*[@key='10']" fromNamePath="Record/Elements/Quantity" fromType="profile" toKey="18" toKeyPath="*[@key='5']/*[@key='12']/*[@key='13']/*[@key='18']" toNamePath="Statement/Statement/Fields/Qty" toType="profile"/></Mappings><Functions/><Defaults/><DocumentCacheJoins/></Map></bns:object></bns:Component>