<?xml version="1.0" encoding="UTF-8" standalone="yes"?><bns:Component xmlns:xsi="http://www.w3.org/2001/XMLSchema-instance" xmlns:bns="http://api.platform.boomi.com/" folderFullPath="Cgfns International, Inc./Sandbox Process Library" componentId="2f35288f-be46-4360-b407-4f65e4345cb5" version="1" name="Account Delete (Return Errors)" type="connector-action" subType="salesforce" createdDate="2019-08-20T14:53:13Z" createdBy="gtopakas@cgfns.org" modifiedDate="2019-08-20T14:53:13Z" modifiedBy="gtopakas@cgfns.org" deleted="false" currentVersion="true" folderName="Sandbox Process Library" folderId="RjoyNjI3MDU5" copiedFromComponentId="eaca34ff-9e91-4c3f-b818-da6983cfaed7" copiedFromComponentVersion="1" branchName="main" branchId="QjoyNDQyNTI"><bns:encryptedValues/><bns:description>The record(s) to delete is identified by supplying one or more internal Salesforce Ids in the Delete Request Profile.</bns:description><bns:object><Operation xmlns=""><Archiving directory="" enabled="false"/><Configuration><SalesforceSendAction batchCount="200" objectAction="delete" objectName="Account" requestProfile="f4442573-9a84-41cf-bcac-7376a167716b" returnApplicationErrors="true" useBulkAPI="false"><Options><Fields><SalesforceObject checkable="false" externalIdField="Choose..." import="true" level="0" name="Account" objectAction="delete" objectType="Account"><FieldList name="FieldList"><SalesforceField custom="false" dataType="character" fEnabled="true" name="Id" nillable="false"/><SalesforceField custom="false" dataType="boolean" fEnabled="true" name="IsDeleted" nillable="false"/><SalesforceField custom="false" dataType="reference" fEnabled="true" name="MasterRecordId" nillable="true"><references relationshipName="MasterRecord" useExternalId="false"><referenceTo objectType="Account"><referenceField custom="false" dataType="character" name="Id"/><referenceField custom="true" dataType="character" name="ExternalID__c"/></referenceTo></references></SalesforceField><SalesforceField custom="false" dataType="character" fEnabled="true" name="Name" nillable="false"/><SalesforceField custom="false" dataType="character" fEnabled="true" name="Type" nillable="true"/><SalesforceField custom="false" dataType="reference" fEnabled="true" name="ParentId" nillable="true"><references relationshipName="Parent" useExternalId="false"><referenceTo objectType="Account"><referenceField custom="false" dataType="character" name="Id"/><referenceField custom="true" dataType="character" name="ExternalID__c"/></referenceTo></references></SalesforceField><SalesforceField custom="false" dataType="character" fEnabled="true" name="BillingStreet" nillable="true"/><SalesforceField custom="false" dataType="character" fEnabled="true" name="BillingCity" nillable="true"/><SalesforceField custom="false" dataType="character" fEnabled="true" name="BillingState" nillable="true"/><SalesforceField custom="false" dataType="character" fEnabled="true" name="BillingPostalCode" nillable="true"/><SalesforceField custom="false" dataType="character" fEnabled="true" name="BillingCountry" nillable="true"/><SalesforceField custom="false" dataType="character" fEnabled="true" name="ShippingStreet" nillable="true"/><SalesforceField custom="false" dataType="character" fEnabled="true" name="ShippingCity" nillable="true"/><SalesforceField custom="false" dataType="character" fEnabled="true" name="ShippingState" nillable="true"/><SalesforceField custom="false" dataType="character" fEnabled="true" name="ShippingPostalCode" nillable="true"/><SalesforceField custom="false" dataType="character" fEnabled="true" name="ShippingCountry" nillable="true"/><SalesforceField custom="false" dataType="character" fEnabled="true" name="Phone" nillable="true"/><SalesforceField custom="false" dataType="character" fEnabled="true" name="Fax" nillable="true"/><SalesforceField custom="false" dataType="character" fEnabled="true" name="AccountNumber" nillable="true"/><SalesforceField custom="false" dataType="character" fEnabled="true" name="Website" nillable="true"/><SalesforceField custom="false" dataType="character" fEnabled="true" name="Sic" nillable="true"/><SalesforceField custom="false" dataType="character" fEnabled="true" name="Industry" nillable="true"/><SalesforceField custom="false" dataType="number" fEnabled="true" name="AnnualRevenue" nillable="true"/><SalesforceField custom="false" dataType="number" fEnabled="true" name="NumberOfEmployees" nillable="true"/><SalesforceField custom="false" dataType="character" fEnabled="true" name="Ownership" nillable="true"/><SalesforceField custom="false" dataType="character" fEnabled="true" name="TickerSymbol" nillable="true"/><SalesforceField custom="false" dataType="character" fEnabled="true" name="Description" nillable="true"/><SalesforceField custom="false" dataType="character" fEnabled="true" name="Rating" nillable="true"/><SalesforceField custom="false" dataType="character" fEnabled="true" name="Site" nillable="true"/><SalesforceField custom="false" dataType="reference" fEnabled="true" name="OwnerId" nillable="false"><references relationshipName="Owner" useExternalId="false"><referenceTo objectType="User"><referenceField custom="false" dataType="character" name="Id"/><referenceField custom="false" dataType="character" name="Username"/><referenceField custom="false" dataType="character" name="Email"/></referenceTo></references></SalesforceField><SalesforceField custom="false" dataType="datetime" fEnabled="true" name="CreatedDate" nillable="false"/><SalesforceField custom="false" dataType="reference" fEnabled="true" name="CreatedById" nillable="false"><references relationshipName="CreatedBy" useExternalId="false"><referenceTo objectType="User"><referenceField custom="false" dataType="character" name="Id"/><referenceField custom="false" dataType="character" name="Username"/><referenceField custom="false" dataType="character" name="Email"/></referenceTo></references></SalesforceField><SalesforceField custom="false" dataType="datetime" fEnabled="true" name="LastModifiedDate" nillable="false"/><SalesforceField custom="false" dataType="reference" fEnabled="true" name="LastModifiedById" nillable="false"><references relationshipName="LastModifiedBy" useExternalId="false"><referenceTo objectType="User"><referenceField custom="false" dataType="character" name="Id"/><referenceField custom="false" dataType="character" name="Username"/><referenceField custom="false" dataType="character" name="Email"/></referenceTo></references></SalesforceField><SalesforceField custom="false" dataType="datetime" fEnabled="true" name="SystemModstamp" nillable="false"/><SalesforceField custom="false" dataType="date" fEnabled="true" name="LastActivityDate" nillable="true"/><SalesforceField custom="false" dataType="character" fEnabled="true" name="CustomerPriority__c" nillable="true"/><SalesforceField custom="false" dataType="character" fEnabled="true" name="SLA__c" nillable="true"/><SalesforceField custom="false" dataType="character" fEnabled="true" name="Active__c" nillable="true"/><SalesforceField custom="false" dataType="number" fEnabled="true" name="NumberofLocations__c" nillable="true"/><SalesforceField custom="false" dataType="character" fEnabled="true" name="UpsellOpportunity__c" nillable="true"/><SalesforceField custom="false" dataType="character" fEnabled="true" name="SLASerialNumber__c" nillable="true"/><SalesforceField custom="false" dataType="date" fEnabled="true" name="SLAExpirationDate__c" nillable="true"/><SalesforceField custom="true" dataType="character" fEnabled="true" name="ExternalID__c" nillable="false"/></FieldList><Filter><SalesforceFilterLogical isRoot="true" logicalOperator="and"/></Filter><Sorts/></SalesforceObject></Fields></Options></SalesforceSendAction></Configuration><Tracking><TrackedFields/></Tracking><Caching/></Operation></bns:object></bns:Component>